dearpygui_map/__init__.py
dearpygui_map/geo.py
dearpygui_map/io.py
dearpygui_map/tile_source.py
dearpygui_map/util.py
dearpygui_map/widget.py
dearpygui_map-0.1.0.dist-info/LICENSE
dearpygui_map-0.1.0.dist-info/WHEEL
dearpygui_map-0.1.0.dist-info/METADATA
dearpygui_map-0.1.0.dist-info/RECORD
