Metadata-Version: 2.1
Name: dearpygui-map
Version: 0.1.0
Summary: Map widget for Dear PyGui
Home-page: https://github.com/mkouhia/dearpygui-map
License: MIT
Author: Mikko Kouhia
Author-email: mikko.kouhia@iki.fi
Requires-Python: >=3.7.0,<4.0.0
Classifier: Development Status :: 1 - Planning
Classifier: License :: OSI Approved :: MIT License
Classifier: Operating System :: OS Independent
Classifier: Programming Language :: Python :: 3
Classifier: Programming Language :: Python :: 3.10
Classifier: Programming Language :: Python :: 3.7
Classifier: Programming Language :: Python :: 3.8
Classifier: Programming Language :: Python :: 3.9
Requires-Dist: dearpygui (>=1.3.1,<2.0.0)
Project-URL: Repository, https://github.com/mkouhia/dearpygui-map
